{"refrec": {"BRefID": 287715, "RR": "<b>Brind'Amour, A.; Laffargue, P.; Morin, J.; Vaz, S.; Foveau, A.; Le Bris, H.</b> (2014). Morphospecies and taxonomic sufficiency of benthic megafauna in scientific bottom trawl surveys. <i>Cont. Shelf Res. 72(1)</i>: 1-9. <a href=\"https://hdl.handle.net/10.1016/j.csr.2013.10.015\" target=\"_blank\">https://hdl.handle.net/10.1016/j.csr.2013.10.015</a>", "BEntID": 279740, "PublicFlag": 1, "CheckedFlag": 1, "wosflag": 1, "vabbflag": 1, "RefStringPartII": ". <i>Cont. Shelf Res. 72(1)</i>: 1-9. <a href=\"https://hdl.handle.net/10.1016/j.csr.2013.10.015\" target=\"_blank\">https://hdl.handle.net/10.1016/j.csr.2013.10.015</a>", "DocTypID": 8, "MarineFlag": 1, "FreshFlag": 0, "BrackishFlag": 0, "TerrestrialFlag": 0, "Authorstring": "Brind'Amour, A.; Laffargue, P.; Morin, J.; Vaz, S.; Foveau, A.; Le Bris, H.", "OrigTitleTranslFlag": 0, "Authorstringtrunc": "Brind'Amour, A. <i>et al.</i>", "Englishabstract": "Scientific fisheries surveys routinely identify a large diversity of commercial and non-commercial benthic megainvertebrates that could provide useful information for Marine Strategy Framework Directive (MSFD) descriptors. Species is obviously the basic taxonomic level to which most ecological studies and theories refer. Identification at this level of organization is indeed always preferred over any other taxonomic level. Nevertheless, aggregation of species to higher taxonomic levels may be unavoidable sometimes, since errors of identification are known or suspected to occur in many surveys. Using analyses of taxonomic sufficiency (identification of organisms at various taxonomic resolutions) and groups of morphospecies (taxa identified easily by non-experts on the basis of evident morphological traits), this study aims to quantify the loss of ecological information incurred by partial identification of benthic megafauna in bottom trawl surveys in order to put such data to good use. The analyses were conducted on five scientific surveys representing a large range of geographical areas (from 150 km<sup>2</sup> to 150 000 km<sup>2</sup>) and environmental conditions. Results show that genus, family and, particularly, morphospecies are good surrogates for species identification in community analyses. We suggest that bottom trawl surveys can provide reliable megafauna data that may usefully complete those obtained by grab surveys. The use of morphospecies could lead to new strategies, combining different datasets to provide indicators for MSFD descriptors (e.g. D6).", "AbstractOtherLang": null, "BibLvlCode": "AS", "StandardTitle": "Morphospecies and taxonomic sufficiency of benthic megafauna in scientific bottom trawl surveys", "OrigTitleLangCode": "en", "UserAccessRight": null, "UserAccID": null, "AuthorKeywords": "Bay of Biscay,English Channel, North Sea, Taxonomic sufficiency, Benthic descriptor, Bottom trawl surveys", "OtherDescriptors": null, "Notes": null, "AnaPub": 2014, "MonPub": null, "DateUpdate": "2018-02-13                    ", "DateCreate": "2017-08-08                    ", "SecASFANote": null, "ProID": null, "ConfID": null, "PeerRev": 1, "VlizCoreFlag": 1, "WoScode": "WOS:000329880000001", "VABBcode": null, "OpenAcc": 0, "Handle": "10.1016/j.csr.2013.10.015"}, "refs": null, "anarec": {"AnaID": 287715, "PubliDate": 2014, "Pagination": "1-9", "XtraPublOfAnaID": null, "ISBN": null, "Volume": "72", "Issue": "1", "BRefMon": null, "BRefMonRR": null, "BRefXtra": null, "BRefXtraRR": null, "SerBRefID": 42769, "SerRR": "Continental Shelf Research. Pergamon Press: Oxford; New York.  ISSN 0278-4343; e-ISSN 1873-6955", "StandardTitleSer": "Continental Shelf Research", "ISSN": "0278-4343", "AbbrevSer": "Cont. Shelf Res.", "StandardTitleMon": null, "StartPage": 1, "Pages": 9, "ToPubliDate": null, "BRefBibLvlCode": "S", "SerNotes": null}, "monrec": null, "serrec": null, "relations": null, "relationsRev": null, "addrec": null, "othpubs": null, "ownerships": null, "authors": [{"AutName": "Brind'Amour", "Firstname": "Anik", "Initials": "A.", "Affiliation": "IFREMER, Dept Ecol & Modeles Halieut, F-44311 Nantes 03, France.", "Discriminator": null, "CorporateFlag": 0, "BEntID": 279740, "AutID": 305467, "OrderNr": 1, "DegrID": null, "EditorFlag": 0, "CorrespFlag": 0, "IllustratorFlag": 0, "ReviserFlag": 0, "TranslatorFlag": 0, "InsAcronym": null, "InsFSN": null, "ORCID": null, "PersID": null, "InsID": null}, {"AutName": "Laffargue", "Firstname": "Pascal", "Initials": "P.", "Affiliation": "IFREMER, Dept Ecol & Modeles Halieut, F-44311 Nantes 03, France.", "Discriminator": null, "CorporateFlag": 0, "BEntID": 279740, "AutID": 305468, "OrderNr": 2, "DegrID": null, "EditorFlag": 0, "CorrespFlag": 0, "IllustratorFlag": 0, "ReviserFlag": 0, "TranslatorFlag": 0, "InsAcronym": null, "InsFSN": null, "ORCID": null, "PersID": null, "InsID": null}, {"AutName": "Morin", "Firstname": "Jocelyne", "Initials": "J.", "Affiliation": "IFREMER, Lab Ressources Halieut, F-14520 Port En Bessin, France.", "Discriminator": null, "CorporateFlag": 0, "BEntID": 279740, "AutID": 305469, "OrderNr": 3, "DegrID": null, "EditorFlag": 0, "CorrespFlag": 0, "IllustratorFlag": 0, "ReviserFlag": 0, "TranslatorFlag": 0, "InsAcronym": null, "InsFSN": null, "ORCID": null, "PersID": null, "InsID": null}, {"AutName": "Vaz", "Firstname": "Sandrine", "Initials": "S.", "Affiliation": "IFREMER, F-62321 Boulogne Sur Mer, France.", "Discriminator": null, "CorporateFlag": 0, "BEntID": 279740, "AutID": 305470, "OrderNr": 4, "DegrID": null, "EditorFlag": 0, "CorrespFlag": 0, "IllustratorFlag": 0, "ReviserFlag": 0, "TranslatorFlag": 0, "InsAcronym": null, "InsFSN": null, "ORCID": null, "PersID": null, "InsID": null}, {"AutName": "Foveau", "Firstname": "Aur\u00e9lie", "Initials": "A.", "Affiliation": "CRESCO IFREMER, Lab Environm Littoral, Stn Dinard, F-35801 Dinard, France.", "Discriminator": null, "CorporateFlag": 0, "BEntID": 279740, "AutID": 305471, "OrderNr": 5, "DegrID": null, "EditorFlag": 0, "CorrespFlag": 0, "IllustratorFlag": 0, "ReviserFlag": 0, "TranslatorFlag": 0, "InsAcronym": null, "InsFSN": null, "ORCID": null, "PersID": null, "InsID": null}, {"AutName": "Le Bris", "Firstname": "Herv\u00e9", "Initials": "H.", "Affiliation": "Univ Europeenne Bretagne, Agrocampus Ouest, UMR Ecol & Sante Ecosyst 985, F-35042 Rennes, France.", "Discriminator": null, "CorporateFlag": 0, "BEntID": 279740, "AutID": 305472, "OrderNr": 6, "DegrID": null, "EditorFlag": 0, "CorrespFlag": 0, "IllustratorFlag": 0, "ReviserFlag": 0, "TranslatorFlag": 0, "InsAcronym": null, "InsFSN": null, "ORCID": null, "PersID": null, "InsID": null}], "mapdetails": null, "datasets": null, "monographs": null, "monparts": null, "serparts": null, "BEntOpen": null, "BEntPrivate": null, "availability": [{"BInstID": null, "LibID": 36, "BRefID": "287715", "Acronym": "VLIZ", "Library": "Vlaams Instituut voor de Zee", "ReqLink": 1, "InternalReq": 1, "LoggedInReq": 1, "InsPub": 1, "InsID": 36, "PublicFlag": 1}], "litstyles": null, "thespers": null, "conf": null, "proj": null, "Physdatasets": null, "spcols": {"941": {"SpName": "LifeWatch Species Information Backbone", "SpColID": 941, "ParSpColID": 39, "TopParID": 39, "ShortName": "LifeWatch Species Information Backbone", "URLLocation": null, "LibID": 36, "OpenRepoFlag": null, "SpTypID": null, "TopParIDNotWebsite": 39, "SpColPath": "VLIZ ackn/LifeWatch Species Information Backbone"}, "39": {"SpName": "VLIZ Acknowledged Publications", "SpColID": 39, "ParSpColID": null, "TopParID": null, "ShortName": "VLIZ ackn", "URLLocation": null, "LibID": 36, "OpenRepoFlag": null, "SpTypID": null, "TopParIDNotWebsite": null, "SpColPath": "VLIZ ackn"}, "": {"SpName": "VLIZ Core Flag", "SpColID": null, "ParSpColID": null, "TopParID": null, "ShortName": null, "URLLocation": null, "LibID": null, "OpenRepoFlag": null, "SpTypID": 1, "TopParIDNotWebsite": null, "SpColPath": null}, "507": {"SpName": "World Register of Marine Species", "SpColID": 507, "ParSpColID": null, "TopParID": null, "ShortName": "WoRMS website", "URLLocation": null, "LibID": null, "OpenRepoFlag": null, "SpTypID": null, "TopParIDNotWebsite": null, "SpColPath": "WoRMS website"}, "915": {"SpName": "World Register of Marine Species (WoRMS) acknowledged", "SpColID": 915, "ParSpColID": 941, "TopParID": 39, "ShortName": "WoRMS ackn", "URLLocation": null, "LibID": 36, "OpenRepoFlag": null, "SpTypID": null, "TopParIDNotWebsite": 39, "SpColPath": "VLIZ ackn/LifeWatch Species Information Backbone/WoRMS ackn"}, "947": {"SpName": "WoRMS ackn - direct reference", "SpColID": 947, "ParSpColID": 915, "TopParID": 39, "ShortName": "WoRMS ackn - direct", "URLLocation": null, "LibID": 36, "OpenRepoFlag": null, "SpTypID": null, "TopParIDNotWebsite": 39, "SpColPath": "VLIZ ackn/LifeWatch Species Information Backbone/WoRMS ackn/WoRMS ackn - direct"}}, "doi": null, "MParts": null, "SParts": null, "hLibs": null, "langs": [{"BEntID": 279740, "LangCode": "en", "AbstractFlag": 0}, {"BEntID": 279740, "LangCode": "en", "AbstractFlag": 1}], "urls": [{"URL": "https://hdl.handle.net/10.1016/j.csr.2013.10.015", "externalID": "10.1016/j.csr.2013.10.015", "URLTypeCode": "Handle", "URLID": 56777, "URLTypID": 32, "URLType": "Handle", "URLPrefix": "https://hdl.handle.net/"}], "thesterms": null, "taxterms": null, "geoterms": null, "othterms": null, "asfacodes": null, "asfa2codes": null, "resmessage": "", "complete": 1, "sessions": {"newSesName": "VLIZ2000\\sielc", "newSesDate": {"date": "2017-08-08 08:16:45.377000", "timezone_type": 3, "timezone": "Europe/Brussels"}, "updSesName": "Lyssens, Liesbeth, L.", "updSesDate": {"date": "2018-02-13 19:34:46.407000", "timezone_type": 3, "timezone": "Europe/Brussels"}}, "arch2discl": null, "SERpubls": [{"PublName": "Pergamon Press", "City": "Oxford; New York"}], "pictures": [], "collections": [{"Collection": "VLIZ Acknowledged Publications", "ShortName": "VLIZ ackn"}]}