{"refrec": {"BRefID": 331856, "RR": "<b>Allouche, M.; Nasri, A.; Harrath, A.M.; Mansour, L.; Beyrem, H.; Boufahja, F.</b> (2021). Experimental selection of <i>Marylynnia puncticaudata</i> (Cyatholaimidae, Nematoda) and effects of organic enrichment. <i>Environm. Sc. & Poll. Res. 28</i>: 6866-6876. <a href=\"https://hdl.handle.net/10.1007/s11356-020-11050-1\" target=\"_blank\">https://hdl.handle.net/10.1007/s11356-020-11050-1</a>", "BEntID": 325468, "PublicFlag": 1, "CheckedFlag": 0, "wosflag": 1, "vabbflag": 1, "RefStringPartII": ". <i>Environm. Sc. & Poll. Res. 28</i>: 6866-6876. <a href=\"https://hdl.handle.net/10.1007/s11356-020-11050-1\" target=\"_blank\">https://hdl.handle.net/10.1007/s11356-020-11050-1</a>", "DocTypID": 8, "MarineFlag": 1, "FreshFlag": 0, "BrackishFlag": 0, "TerrestrialFlag": 0, "Authorstring": "Allouche, M.; Nasri, A.; Harrath, A.M.; Mansour, L.; Beyrem, H.; Boufahja, F.", "OrigTitleTranslFlag": 0, "Authorstringtrunc": "Allouche, M. <i>et al.</i>", "Englishabstract": "Meiobenthic nematodes are well-known bioindicators in aquatic ecosystem health programs. However, the explored taxa are still limited and practically devoted to the community level. The present study provided a new method of experimental isolation of a species from a pristine nematofauna. In our method, the nematofauna faced two types of sediment, namely, the leaves of <i>Posidonia oceanica</i> and shells of <i>Mytilus galloprovincialis</i>, under controlled laboratory conditions, and several changes in species composition occurred through gradual selection of the most adaptable nematode taxa to the new environments, which were previously defaunated. We used the selected nematode taxon, <i>Marylynnia puncticaudata</i> (Cyatholaimidae), to examine the possible effects of organic enrichment, and the results clearly showed that the body size of the nematodes significantly increased and they became fat when after enrichment using a powder made of marine agar (1200\u00a0mg\u00a0l<sup>\u22121</sup>) and cuticles of <i>Crangon crangon</i> (900\u00a0mg\u00a0l<sup>\u22121</sup>), but their relative body growth showed no discernible changes.", "AbstractOtherLang": "  ", "BibLvlCode": "AS", "StandardTitle": "Experimental selection of <i>Marylynnia puncticaudata</i> (Cyatholaimidae, Nematoda) and effects of organic enrichment", "OrigTitleLangCode": "en", "UserAccessRight": null, "UserAccID": null, "AuthorKeywords": "Experimental selection, Organic enrichment, Marine agar", "OtherDescriptors": null, "Notes": null, "AnaPub": 2021, "MonPub": null, "DateUpdate": "2021-02-02                    ", "DateCreate": "2020-12-09                    ", "SecASFANote": null, "ProID": null, "ConfID": null, "PeerRev": 1, "VlizCoreFlag": 1, "WoScode": "WOS:000574802300012", "VABBcode": null, "OpenAcc": 0, "Handle": "10.1007/s11356-020-11050-1"}, "refs": null, "anarec": {"AnaID": 331856, "PubliDate": 2021, "Pagination": "6866-6876", "XtraPublOfAnaID": null, "ISBN": null, "Volume": "28", "Issue": null, "BRefMon": null, "BRefMonRR": null, "BRefXtra": null, "BRefXtraRR": null, "SerBRefID": 45312, "SerRR": "Environmental Science and Pollution Research. Springer: Heidelberg; Berlin.  ISSN 0944-1344; e-ISSN 1614-7499", "StandardTitleSer": "Environmental Science and Pollution Research", "ISSN": "0944-1344", "AbbrevSer": "Environm. Sc. & Poll. Res.", "StandardTitleMon": null, "StartPage": 6866, "Pages": 11, "ToPubliDate": null, "BRefBibLvlCode": "S", "SerNotes": null}, "monrec": null, "serrec": null, "relations": null, "relationsRev": null, "addrec": null, "othpubs": null, "ownerships": null, "authors": [{"AutName": "Allouche", "Firstname": "Mohamed", "Initials": "M.", "Affiliation": null, "Discriminator": null, "CorporateFlag": 0, "BEntID": 325468, "AutID": 398175, "OrderNr": 1, "DegrID": null, "EditorFlag": 0, "CorrespFlag": 0, "IllustratorFlag": 0, "ReviserFlag": 0, "TranslatorFlag": 0, "InsAcronym": null, "InsFSN": null, "ORCID": null, "PersID": null, "InsID": null}, {"AutName": "Nasri", "Firstname": "Ahmed", "Initials": "A.", "Affiliation": null, "Discriminator": null, "CorporateFlag": 0, "BEntID": 325468, "AutID": 385559, "OrderNr": 2, "DegrID": null, "EditorFlag": 0, "CorrespFlag": 0, "IllustratorFlag": 0, "ReviserFlag": 0, "TranslatorFlag": 0, "InsAcronym": null, "InsFSN": null, "ORCID": null, "PersID": null, "InsID": null}, {"AutName": "Harrath", "Firstname": "Abdel Halim", "Initials": "A.M.", "Affiliation": null, "Discriminator": null, "CorporateFlag": 0, "BEntID": 325468, "AutID": 401979, "OrderNr": 3, "DegrID": null, "EditorFlag": 0, "CorrespFlag": 0, "IllustratorFlag": 0, "ReviserFlag": 0, "TranslatorFlag": 0, "InsAcronym": null, "InsFSN": null, "ORCID": null, "PersID": null, "InsID": null}, {"AutName": "Mansour", "Firstname": "Lamjed", "Initials": "L.", "Affiliation": null, "Discriminator": null, "CorporateFlag": 0, "BEntID": 325468, "AutID": 398177, "OrderNr": 4, "DegrID": null, "EditorFlag": 0, "CorrespFlag": 0, "IllustratorFlag": 0, "ReviserFlag": 0, "TranslatorFlag": 0, "InsAcronym": null, "InsFSN": null, "ORCID": null, "PersID": null, "InsID": null}, {"AutName": "Beyrem", "Firstname": "Hamouda", "Initials": "H.", "Affiliation": null, "Discriminator": null, "CorporateFlag": 0, "BEntID": 325468, "AutID": 30156, "OrderNr": 5, "DegrID": null, "EditorFlag": 0, "CorrespFlag": 0, "IllustratorFlag": 0, "ReviserFlag": 0, "TranslatorFlag": 0, "InsAcronym": null, "InsFSN": null, "ORCID": null, "PersID": null, "InsID": null}, {"AutName": "Boufahja", "Firstname": "Fehmi", "Initials": "F.", "Affiliation": null, "Discriminator": null, "CorporateFlag": 0, "BEntID": 325468, "AutID": 74062, "OrderNr": 6, "DegrID": null, "EditorFlag": 0, "CorrespFlag": 0, "IllustratorFlag": 0, "ReviserFlag": 0, "TranslatorFlag": 0, "InsAcronym": null, "InsFSN": null, "ORCID": null, "PersID": null, "InsID": null}], "mapdetails": null, "datasets": null, "monographs": null, "monparts": null, "serparts": null, "BEntOpen": null, "BEntPrivate": null, "availability": [{"BInstID": null, "LibID": 36, "BRefID": "331856", "Acronym": "VLIZ", "Library": "Vlaams Instituut voor de Zee", "ReqLink": 1, "InternalReq": 1, "LoggedInReq": 1, "InsPub": 1, "InsID": 36, "PublicFlag": 1}], "litstyles": null, "thespers": null, "conf": null, "proj": null, "Physdatasets": null, "spcols": {"941": {"SpName": "LifeWatch Species Information Backbone", "SpColID": 941, "ParSpColID": 39, "TopParID": 39, "ShortName": "LifeWatch Species Information Backbone", "URLLocation": null, "LibID": 36, "OpenRepoFlag": null, "SpTypID": null, "TopParIDNotWebsite": 39, "SpColPath": "VLIZ ackn/LifeWatch Species Information Backbone"}, "39": {"SpName": "VLIZ Acknowledged Publications", "SpColID": 39, "ParSpColID": null, "TopParID": null, "ShortName": "VLIZ ackn", "URLLocation": null, "LibID": 36, "OpenRepoFlag": null, "SpTypID": null, "TopParIDNotWebsite": null, "SpColPath": "VLIZ ackn"}, "": {"SpName": "VLIZ Core Flag", "SpColID": null, "ParSpColID": null, "TopParID": null, "ShortName": null, "URLLocation": null, "LibID": null, "OpenRepoFlag": null, "SpTypID": 1, "TopParIDNotWebsite": null, "SpColPath": null}, "507": {"SpName": "World Register of Marine Species", "SpColID": 507, "ParSpColID": null, "TopParID": null, "ShortName": "WoRMS website", "URLLocation": null, "LibID": null, "OpenRepoFlag": null, "SpTypID": null, "TopParIDNotWebsite": null, "SpColPath": "WoRMS website"}, "915": {"SpName": "World Register of Marine Species (WoRMS) acknowledged", "SpColID": 915, "ParSpColID": 941, "TopParID": 39, "ShortName": "WoRMS ackn", "URLLocation": null, "LibID": 36, "OpenRepoFlag": null, "SpTypID": null, "TopParIDNotWebsite": 39, "SpColPath": "VLIZ ackn/LifeWatch Species Information Backbone/WoRMS ackn"}, "947": {"SpName": "WoRMS ackn - direct reference", "SpColID": 947, "ParSpColID": 915, "TopParID": 39, "ShortName": "WoRMS ackn - direct", "URLLocation": null, "LibID": 36, "OpenRepoFlag": null, "SpTypID": null, "TopParIDNotWebsite": 39, "SpColPath": "VLIZ ackn/LifeWatch Species Information Backbone/WoRMS ackn/WoRMS ackn - direct"}}, "doi": null, "MParts": null, "SParts": null, "hLibs": null, "langs": [{"BEntID": 325468, "LangCode": "en", "AbstractFlag": 0}, {"BEntID": 325468, "LangCode": "en", "AbstractFlag": 1}], "urls": [{"URL": "https://hdl.handle.net/10.1007/s11356-020-11050-1", "externalID": "10.1007/s11356-020-11050-1", "URLTypeCode": "Handle", "URLID": 88559, "URLTypID": 32, "URLType": "Handle", "URLPrefix": "https://hdl.handle.net/"}], "thesterms": null, "taxterms": [{"TaxTerm": "Crangon crangon (Linnaeus, 1758) [Gewone garnaal]", "AphiaID": 107552, "TaxtID": 16758}, {"TaxTerm": "Marylynnia puncticaudata", "AphiaID": 836783, "TaxtID": 48455}, {"TaxTerm": "Mytilus galloprovincialis [diepwatermossel]", "AphiaID": 140481, "TaxtID": 36457}, {"TaxTerm": "Posidonia oceanica [neptunusgras]", "AphiaID": 145794, "TaxtID": 23930}], "geoterms": null, "othterms": null, "asfacodes": null, "asfa2codes": null, "resmessage": "", "complete": 1, "sessions": {"newSesName": "Chisala, Chilekwa, C.", "newSesDate": {"date": "2020-12-09 09:51:42.993000", "timezone_type": 3, "timezone": "Europe/Brussels"}, "updSesName": "Bouchti, Zohra, Z.", "updSesDate": {"date": "2021-02-02 06:27:37.040000", "timezone_type": 3, "timezone": "Europe/Brussels"}}, "arch2discl": null, "SERpubls": [{"PublName": "Springer", "City": "Heidelberg; Berlin"}], "pictures": [], "taxtermsASFA": [{"TaxTerm": "Crangon crangon (Linnaeus, 1758)"}, {"TaxTerm": "Marylynnia puncticaudata"}, {"TaxTerm": "Mytilus galloprovincialis"}, {"TaxTerm": "Posidonia oceanica"}], "collections": [{"Collection": "VLIZ Acknowledged Publications", "ShortName": "VLIZ ackn"}]}