{"refrec": {"BRefID": 339940, "RR": "<b>Kozuch, L.</b> (2021). Cahokia's Mound 72 shell artifacts. <i>Southeastern Archaeology 40(1)</i>: 33-47. <a href=\"https://dx.doi.org/10.1080/0734578x.2021.1873057\" target=\"_blank\">https://dx.doi.org/10.1080/0734578x.2021.1873057</a>", "BEntID": 336575, "PublicFlag": 1, "CheckedFlag": 0, "wosflag": 0, "vabbflag": 0, "RefStringPartII": ". <i>Southeastern Archaeology 40(1)</i>: 33-47. <a href=\"https://dx.doi.org/10.1080/0734578x.2021.1873057\" target=\"_blank\">https://dx.doi.org/10.1080/0734578x.2021.1873057</a>", "DocTypID": 8, "MarineFlag": 0, "FreshFlag": 0, "BrackishFlag": 0, "TerrestrialFlag": 0, "Authorstring": "Kozuch, L.", "OrigTitleTranslFlag": 0, "Authorstringtrunc": "Kozuch, L.", "Englishabstract": "Around AD 1050 at Cahokia, a sudden coalescence of peoples with new ceremonials and Mound 72's commemorative human interments provide evidence of long\u2013distance contacts and finely crafted artifacts. Beads from the famous Mound 72 Beaded Burial have remained unstudied since they were unearthed-a strange situation given the importance of the Beaded Burial. This article presents results from my reexamination of all shell artifacts from Mound 72, including some new artifact identifications, bead counts, and measurements. Artifacts previously called gorgets are shell cups, and one was remarkably large. The source was probably the eastern Gulf of Mexico for most marine shells. I present a new method of examining bead drill holes using the frustum formula, suggesting that porcupine quills or biological materials were used as drill tips for columella beads. This method can be used on stone and bone beads as well. I hypothesize a general decline in bead crafting through time. Paired shell artifact emplacements throughout Mound 72 echo the paired male/female human interments from the Beaded Burial, adding to evidence that Mound 72's burials were part of a ritual theater. My analysis supports the contention that marine shell artifacts were symbolic conduits of human spirits and power.", "AbstractOtherLang": null, "BibLvlCode": "AS", "StandardTitle": "Cahokia's Mound 72 shell artifacts", "OrigTitleLangCode": "en", "UserAccessRight": null, "UserAccID": null, "AuthorKeywords": "Cahokia; Mound 72; shell cups; shell beads; symbols; Mississippian", "OtherDescriptors": null, "Notes": null, "AnaPub": 2021, "MonPub": null, "DateUpdate": "2021-07-09                    ", "DateCreate": "2021-07-09                    ", "SecASFANote": null, "ProID": null, "ConfID": null, "PeerRev": 1, "VlizCoreFlag": 1, "WoScode": null, "VABBcode": null, "OpenAcc": 0, "DOI": "10.1080/0734578x.2021.1873057"}, "refs": null, "anarec": {"AnaID": 339940, "PubliDate": 2021, "Pagination": "33-47", "XtraPublOfAnaID": null, "ISBN": null, "Volume": "40", "Issue": "1", "BRefMon": null, "BRefMonRR": null, "BRefXtra": null, "BRefXtraRR": null, "SerBRefID": 339939, "SerRR": "Southeastern Archaeology. Taylor & Francis: UK.  ISSN 0734-578X; e-ISSN 2168-4723", "StandardTitleSer": "Southeastern Archaeology", "ISSN": "0734-578X", "AbbrevSer": null, "StandardTitleMon": null, "StartPage": 33, "Pages": 15, "ToPubliDate": null, "BRefBibLvlCode": "S", "SerNotes": null}, "monrec": null, "serrec": null, "relations": null, "relationsRev": null, "addrec": null, "othpubs": null, "ownerships": null, "authors": [{"AutName": "Kozuch", "Firstname": "Laura", "Initials": "L.", "Affiliation": null, "Discriminator": null, "CorporateFlag": 0, "BEntID": 336575, "AutID": 460439, "OrderNr": 1, "DegrID": null, "EditorFlag": 0, "CorrespFlag": 0, "IllustratorFlag": 0, "ReviserFlag": 0, "TranslatorFlag": 0, "InsAcronym": null, "InsFSN": null, "ORCID": null, "PersID": null, "InsID": null}], "mapdetails": null, "datasets": null, "monographs": null, "monparts": null, "serparts": null, "BEntOpen": null, "BEntPrivate": null, "availability": [{"BInstID": null, "LibID": 36, "BRefID": "339940", "Acronym": "VLIZ", "Library": "Vlaams Instituut voor de Zee", "ReqLink": 1, "InternalReq": 1, "LoggedInReq": 1, "InsPub": 1, "InsID": 36, "PublicFlag": 1}], "litstyles": null, "thespers": null, "conf": null, "proj": null, "Physdatasets": null, "spcols": {"941": {"SpName": "LifeWatch Species Information Backbone", "SpColID": 941, "ParSpColID": 39, "TopParID": 39, "ShortName": "LifeWatch Species Information Backbone", "URLLocation": null, "LibID": 36, "OpenRepoFlag": null, "SpTypID": null, "TopParIDNotWebsite": 39, "SpColPath": "VLIZ ackn/LifeWatch Species Information Backbone"}, "39": {"SpName": "VLIZ Acknowledged Publications", "SpColID": 39, "ParSpColID": null, "TopParID": null, "ShortName": "VLIZ ackn", "URLLocation": null, "LibID": 36, "OpenRepoFlag": null, "SpTypID": null, "TopParIDNotWebsite": null, "SpColPath": "VLIZ ackn"}, "": {"SpName": "VLIZ Core Flag", "SpColID": null, "ParSpColID": null, "TopParID": null, "ShortName": null, "URLLocation": null, "LibID": null, "OpenRepoFlag": null, "SpTypID": 1, "TopParIDNotWebsite": null, "SpColPath": null}, "507": {"SpName": "World Register of Marine Species", "SpColID": 507, "ParSpColID": null, "TopParID": null, "ShortName": "WoRMS website", "URLLocation": null, "LibID": null, "OpenRepoFlag": null, "SpTypID": null, "TopParIDNotWebsite": null, "SpColPath": "WoRMS website"}, "915": {"SpName": "World Register of Marine Species (WoRMS) acknowledged", "SpColID": 915, "ParSpColID": 941, "TopParID": 39, "ShortName": "WoRMS ackn", "URLLocation": null, "LibID": 36, "OpenRepoFlag": null, "SpTypID": null, "TopParIDNotWebsite": 39, "SpColPath": "VLIZ ackn/LifeWatch Species Information Backbone/WoRMS ackn"}, "947": {"SpName": "WoRMS ackn - direct reference", "SpColID": 947, "ParSpColID": 915, "TopParID": 39, "ShortName": "WoRMS ackn - direct", "URLLocation": null, "LibID": 36, "OpenRepoFlag": null, "SpTypID": null, "TopParIDNotWebsite": 39, "SpColPath": "VLIZ ackn/LifeWatch Species Information Backbone/WoRMS ackn/WoRMS ackn - direct"}}, "doi": null, "MParts": null, "SParts": null, "hLibs": null, "langs": [{"BEntID": 336575, "LangCode": "en", "AbstractFlag": 0}, {"BEntID": 336575, "LangCode": "en", "AbstractFlag": 1}], "urls": [{"URL": "https://dx.doi.org/10.1080/0734578x.2021.1873057", "externalID": "10.1080/0734578x.2021.1873057", "URLTypeCode": "DOI", "URLID": 95191, "URLTypID": 13, "URLType": "DOI", "URLPrefix": "http://dx.doi.org/"}], "thesterms": null, "taxterms": null, "geoterms": null, "othterms": null, "asfacodes": null, "asfa2codes": null, "resmessage": "", "complete": 1, "sessions": {"newSesName": "Bouchti, Zohra, Z.", "newSesDate": {"date": "2021-07-09 08:18:14.403000", "timezone_type": 3, "timezone": "Europe/Brussels"}, "updSesName": "Bouchti, Zohra, Z.", "updSesDate": {"date": "2021-07-09 08:18:14.403000", "timezone_type": 3, "timezone": "Europe/Brussels"}}, "arch2discl": null, "SERpubls": [{"PublName": "Taylor & Francis", "City": "UK"}], "pictures": [], "collections": [{"Collection": "VLIZ Acknowledged Publications", "ShortName": "VLIZ ackn"}]}