{"refrec": {"BRefID": 340823, "RR": "<b>Gates, A.R.; Durden, J.M.; Richmond, M.D.; Muhando, C.A.; Khamis, Z.A.; Jones, D.O.B.</b> (2021). Ecological considerations for marine spatial management in deep-water Tanzania. <i>Ocean Coast. Manag. 210</i>: 105703. <a href=\"https://dx.doi.org/10.1016/j.ocecoaman.2021.105703\" target=\"_blank\">https://dx.doi.org/10.1016/j.ocecoaman.2021.105703</a>", "BEntID": 337458, "PublicFlag": 1, "CheckedFlag": 0, "wosflag": 1, "vabbflag": 1, "RefStringPartII": ". <i>Ocean Coast. Manag. 210</i>: 105703. <a href=\"https://dx.doi.org/10.1016/j.ocecoaman.2021.105703\" target=\"_blank\">https://dx.doi.org/10.1016/j.ocecoaman.2021.105703</a>", "DocTypID": 8, "MarineFlag": 0, "FreshFlag": 0, "BrackishFlag": 0, "TerrestrialFlag": 0, "Authorstring": "Gates, A.R.; Durden, J.M.; Richmond, M.D.; Muhando, C.A.; Khamis, Z.A.; Jones, D.O.B.", "OrigTitleTranslFlag": 0, "Authorstringtrunc": "Gates, A.R. <i>et al.</i>", "Englishabstract": "The United Republic of Tanzania has jurisdiction over a large marine area (223,000 km<sup>2</sup>) of which over 92% is deeper than 200 m. These deep areas extend from, in most cases <10 km from shore, have connections to shallow and coastal marine habitats through oceanographic processes, and support important living and non-living resources, which are becoming increasingly exploited to support a valuable blue economy. Recognising the need for sustainable development, implementation of conservation and management measures in Tanzania's offshore waters has begun, with the development of coastal protected areas and marine spatial plans (e.g. the Coastal and Marine Spatial Plan for Zanzibar). As yet, the deeper areas of Tanzania have not been considered in marine spatial planning. Here we present a synthesis of available data on the habitats and biological communities of deep-water Tanzania, including new data collected in collaboration with the deep-water oil and gas industry, to provide an indication of regional-scale patterns and areas of potential importance. We also discuss the value and multiple uses of the deep ocean areas to Tanzania, and assess the ecological effects of impacts in these environments. This information is valuable to the Tanzanian government to help inform development of management measures to continue to make sustainable use of valuable deep-water resources. To facilitate uptake, we provide a series of recommendations on considering the Tanzanian deep ocean areas in marine spatial planning to boost future management of the important and sensitive offshore domain.", "AbstractOtherLang": null, "BibLvlCode": "AS", "StandardTitle": "Ecological considerations for marine spatial management in deep-water Tanzania", "OrigTitleLangCode": "en", "UserAccessRight": null, "UserAccID": null, "AuthorKeywords": "Marine spatial planning; Hydrocarbon exploration; East Africa coastal current (EACC)", "OtherDescriptors": null, "Notes": null, "AnaPub": 2021, "MonPub": null, "DateUpdate": "2021-08-04                    ", "DateCreate": "2021-08-04                    ", "SecASFANote": null, "ProID": null, "ConfID": null, "PeerRev": 1, "VlizCoreFlag": 1, "WoScode": null, "VABBcode": null, "OpenAcc": 0, "DOI": "10.1016/j.ocecoaman.2021.105703"}, "refs": null, "anarec": {"AnaID": 340823, "PubliDate": 2021, "Pagination": "105703", "XtraPublOfAnaID": null, "ISBN": null, "Volume": "210", "Issue": null, "BRefMon": null, "BRefMonRR": null, "BRefXtra": null, "BRefXtraRR": null, "SerBRefID": 43586, "SerRR": "Ocean & Coastal Management. Elsevier Science: Barking.  ISSN 0964-5691; e-ISSN 1873-524X", "StandardTitleSer": "Ocean & Coastal Management", "ISSN": "0964-5691", "AbbrevSer": "Ocean Coast. Manag.", "StandardTitleMon": null, "StartPage": null, "Pages": null, "ToPubliDate": null, "BRefBibLvlCode": "S", "SerNotes": null}, "monrec": null, "serrec": null, "relations": null, "relationsRev": null, "addrec": null, "othpubs": null, "ownerships": null, "authors": [{"AutName": "Gates", "Firstname": "Andrew", "Initials": "A.R.", "Affiliation": null, "Discriminator": null, "CorporateFlag": 0, "BEntID": 337458, "AutID": 262944, "OrderNr": 1, "DegrID": null, "EditorFlag": 0, "CorrespFlag": 0, "IllustratorFlag": 0, "ReviserFlag": 0, "TranslatorFlag": 0, "InsAcronym": null, "InsFSN": null, "ORCID": null, "PersID": null, "InsID": null}, {"AutName": "Durden", "Firstname": "Jennifer", "Initials": "J.M.", "Affiliation": null, "Discriminator": null, "CorporateFlag": 0, "BEntID": 337458, "AutID": 238396, "OrderNr": 2, "DegrID": null, "EditorFlag": 0, "CorrespFlag": 0, "IllustratorFlag": 0, "ReviserFlag": 0, "TranslatorFlag": 0, "InsAcronym": null, "InsFSN": null, "ORCID": null, "PersID": null, "InsID": null}, {"AutName": "Richmond", "Firstname": "Matthew", "Initials": "M.D.", "Affiliation": null, "Discriminator": null, "CorporateFlag": 0, "BEntID": 337458, "AutID": 15489, "OrderNr": 3, "DegrID": null, "EditorFlag": 0, "CorrespFlag": 0, "IllustratorFlag": 0, "ReviserFlag": 0, "TranslatorFlag": 0, "InsAcronym": null, "InsFSN": null, "ORCID": null, "PersID": null, "InsID": null}, {"AutName": "Muhando", "Firstname": null, "Initials": "C.A.", "Affiliation": null, "Discriminator": null, "CorporateFlag": 0, "BEntID": 337458, "AutID": 21829, "OrderNr": 4, "DegrID": null, "EditorFlag": 0, "CorrespFlag": 0, "IllustratorFlag": 0, "ReviserFlag": 0, "TranslatorFlag": 0, "InsAcronym": null, "InsFSN": null, "ORCID": null, "PersID": null, "InsID": null}, {"AutName": "Khamis", "Firstname": null, "Initials": "Z.A.", "Affiliation": null, "Discriminator": null, "CorporateFlag": 0, "BEntID": 337458, "AutID": 462251, "OrderNr": 5, "DegrID": null, "EditorFlag": 0, "CorrespFlag": 0, "IllustratorFlag": 0, "ReviserFlag": 0, "TranslatorFlag": 0, "InsAcronym": null, "InsFSN": null, "ORCID": null, "PersID": null, "InsID": null}, {"AutName": "Jones", "Firstname": null, "Initials": "D.O.B.", "Affiliation": null, "Discriminator": null, "CorporateFlag": 0, "BEntID": 337458, "AutID": 233612, "OrderNr": 6, "DegrID": null, "EditorFlag": 0, "CorrespFlag": 0, "IllustratorFlag": 0, "ReviserFlag": 0, "TranslatorFlag": 0, "InsAcronym": null, "InsFSN": null, "ORCID": null, "PersID": null, "InsID": null}], "mapdetails": null, "datasets": null, "monographs": null, "monparts": null, "serparts": null, "BEntOpen": null, "BEntPrivate": null, "availability": [{"BInstID": 364132, "LibID": 36, "BRefID": 340823, "EmbargoDate": null, "FullEmbargoDate": null, "PhysMedID": 16, "hasOCRd": null, "ShelfLocCode": "364132", "BarCode": null, "PaidValue": null, "Medium": "Server", "Description": "Interne VLIZ documenten", "Acronym": "VLIZ", "Library": "Vlaams Instituut voor de Zee", "DutchTerm": "Non-open access", "URL": null, "ClassifID": 228, "Classification": "Non-open access", "ReqLink": 1, "ClassifTypID": 3, "URLLocation": "https://www.vliz.be/imisdocs/publications/", "SubDir": 1, "InternalReq": 1, "LoggedInReq": 1, "Disclaimer": "Disclaimer_VLIZ_Intern", "DutchDisclaimer": "<p>Deze publicatie is enkel beschikbaar voor persoonlijk gebruik binnen de Innovocean site <br />en mag op geen enkele manier verder worden verspreid.</p>", "FileFormat": ".pdf", "FileDescr": "pdf", "InsPub": 1, "InsID": 36, "FileFormID": 6, "PublicFlag": 1, "orderLib": "A"}], "litstyles": null, "thespers": null, "conf": null, "proj": null, "Physdatasets": null, "spcols": {"941": {"SpName": "LifeWatch Species Information Backbone", "SpColID": 941, "ParSpColID": 39, "TopParID": 39, "ShortName": "LifeWatch Species Information Backbone", "URLLocation": null, "LibID": 36, "OpenRepoFlag": null, "SpTypID": null, "TopParIDNotWebsite": 39, "SpColPath": "VLIZ ackn/LifeWatch Species Information Backbone"}, "793": {"SpName": "Marine Regions acknowledged", "SpColID": 793, "ParSpColID": 941, "TopParID": 39, "ShortName": "Marine Regions ackn", "URLLocation": null, "LibID": 36, "OpenRepoFlag": null, "SpTypID": null, "TopParIDNotWebsite": 39, "SpColPath": "VLIZ ackn/LifeWatch Species Information Backbone/Marine Regions ackn"}, "39": {"SpName": "VLIZ Acknowledged Publications", "SpColID": 39, "ParSpColID": null, "TopParID": null, "ShortName": "VLIZ ackn", "URLLocation": null, "LibID": 36, "OpenRepoFlag": null, "SpTypID": null, "TopParIDNotWebsite": null, "SpColPath": "VLIZ ackn"}, "": {"SpName": "VLIZ Core Flag", "SpColID": null, "ParSpColID": null, "TopParID": null, "ShortName": null, "URLLocation": null, "LibID": null, "OpenRepoFlag": null, "SpTypID": 1, "TopParIDNotWebsite": null, "SpColPath": null}}, "doi": null, "MParts": null, "SParts": null, "hLibs": null, "langs": [{"BEntID": 337458, "LangCode": "en", "AbstractFlag": 0}, {"BEntID": 337458, "LangCode": "en", "AbstractFlag": 1}], "urls": [{"URL": "https://dx.doi.org/10.1016/j.ocecoaman.2021.105703", "externalID": "10.1016/j.ocecoaman.2021.105703", "URLTypeCode": "DOI", "URLID": 96015, "URLTypID": 13, "URLType": "DOI", "URLPrefix": "http://dx.doi.org/"}], "thesterms": [{"ThesaurusTerm": "Diepzee", "ThestID": 2145, "Acronym": "ASFA"}, {"ThesaurusTerm": "Onderzeese canyons", "ThestID": 8123, "Acronym": "ASFA"}], "taxterms": null, "geoterms": null, "othterms": null, "asfacodes": null, "asfa2codes": null, "resmessage": "", "complete": 1, "sessions": {"newSesName": "Chisala, Chilekwa, C.", "newSesDate": {"date": "2021-08-04 08:41:02.590000", "timezone_type": 3, "timezone": "Europe/Brussels"}, "updSesName": "Chisala, Chilekwa, C.", "updSesDate": {"date": "2021-08-04 08:41:02.590000", "timezone_type": 3, "timezone": "Europe/Brussels"}}, "arch2discl": null, "SERpubls": [{"PublName": "Elsevier Science", "City": "Barking"}], "pictures": [], "thestermsPath": [{"ThesaurusTerm": "Diepzee", "ThestID": 2145, "Acronym": "ASFA", "ThesTermPath": "Deep sea"}, {"ThesaurusTerm": "Onderzeese canyons", "ThestID": 8123, "Acronym": "ASFA", "ThesTermPath": "Topographic features > Submarine features > Submarine canyons"}], "thestermsASFA": [{"ThesaurusTerm": "Submarine canyons"}], "collections": [{"Collection": "VLIZ Acknowledged Publications", "ShortName": "VLIZ ackn"}]}