{"refrec": {"BRefID": 329678, "RR": "<b>Martin-Cabrera, P.; Lombard, F.; Irisson, J.-O.; Stemmann, L.; M\u00f6ller, K.O.; Lindh, M.; Creach, V.; Schepers, L.</b> (2020). Coordinating efforts to define marine plankton imagery data and metadata best practices and standards. <i>Biodiversity Information Science and Standards 4</i>: e58932. <a href=\"https://hdl.handle.net/10.3897/biss.4.58932\" target=\"_blank\">https://hdl.handle.net/10.3897/biss.4.58932</a>", "BEntID": 323285, "PublicFlag": 1, "CheckedFlag": 0, "wosflag": 0, "vabbflag": 0, "RefStringPartII": ". <i>Biodiversity Information Science and Standards 4</i>: e58932. <a href=\"https://hdl.handle.net/10.3897/biss.4.58932\" target=\"_blank\">https://hdl.handle.net/10.3897/biss.4.58932</a>", "DocTypID": 8, "MarineFlag": 1, "FreshFlag": 0, "BrackishFlag": 0, "TerrestrialFlag": 0, "Authorstring": "Martin-Cabrera, P.; Lombard, F.; Irisson, J.-O.; Stemmann, L.; M\u00f6ller, K.O.; Lindh, M.; Creach, V.; Schepers, L.", "OrigTitleTranslFlag": 0, "Authorstringtrunc": "Martin-Cabrera, P. <i>et al.</i>", "Englishabstract": "\u201cImagery data\u201d can be referred as qualitative and quantitative information from a collection of images. Imaging systems are used more and more frequently in the marine domain to generate huge amounts of imagery data. For example, automatic image classification is used to determine the abundance, size and biomass of plankton communities. In addition, the recent advances of imaging sensors and the growing datasets, highlight the importance of the management and storage capacity of these data. Thus, establishing data standards, optimized data flows and quality control procedures will promote the ability to make these datasets findable, accessible, interoperable and reusable (FAIR principles).At the moment, there are a number of online open-access databases that collect marine biodiversity data, such as the Ocean Biodiversity Information System (OBIS), and more specialized in plankton observations such as the COPEPOD for plankton biomass and ECOTAXA for taxonomic annotation of plankton images. However, they currently lack relevant standards to link metadata of the images.International biodiversity data standards, such as Darwin Core (DwC), are already widely used in OBIS and the Global Biodiversity Information Facility (GBIF). OBIS, has recently adopted the OBIS-ENV-DATA, a format that follows the DwC-Archive (DwC-A) standard, consisting of a DwC Event table in combination with an Occurrence an extended Measurement or Fact table. This structure enables the linkage of quantitative and qualitative properties to both sampling events and species occurrences. It also includes additional fields for property standardization, such as the BODC (British Oceanographic Data Centre) controlled vocabularies, the World Register of Marine Species (WoRMS), which provides crucial quality control support for taxonomic data, and Marine Regions, a database that provides standardized marine georeferenced place names and areas. However, there are no clear guidelines on how to include imagery metadata and derived data in OBIS-ENV-DATA.During this TDWG 2020 symposium, we would like to present and discuss our ongoing work to establish best practices and standardized protocols for imaging data and metadata acquired by a large spectrum of bio-optic sensors. Furthermore, we highlight how the integration of the metadata will flow to existing biodiversity data portals, the European EMODnet Biology portal, (EurOBIS) and OBIS.", "AbstractOtherLang": null, "BibLvlCode": "AS", "StandardTitle": "Coordinating efforts to define marine plankton imagery data and metadata best practices and standards", "OrigTitleLangCode": "en", "UserAccessRight": null, "UserAccID": null, "AuthorKeywords": "imagery data, data standardization, Darwin Core Archive, species occurrence, plankton", "OtherDescriptors": null, "Notes": null, "AnaPub": 2020, "MonPub": null, "DateUpdate": "2020-11-10                    ", "DateCreate": "2020-09-30                    ", "SecASFANote": null, "ProID": null, "ConfID": null, "PeerRev": 1, "VlizCoreFlag": 1, "WoScode": null, "VABBcode": null, "OpenAcc": 1, "Handle": "10.3897/biss.4.58932"}, "refs": null, "anarec": {"AnaID": 329678, "PubliDate": 2020, "Pagination": "e58932", "XtraPublOfAnaID": null, "ISBN": null, "Volume": "4", "Issue": null, "BRefMon": null, "BRefMonRR": null, "BRefXtra": null, "BRefXtraRR": null, "SerBRefID": 290943, "SerRR": "Biodiversity Information Science and Standards. Pensoft Publishers: Sofia.  ISSN 2535-0897", "StandardTitleSer": "Biodiversity Information Science and Standards", "ISSN": "2535-0897", "AbbrevSer": null, "StandardTitleMon": null, "StartPage": null, "Pages": null, "ToPubliDate": null, "BRefBibLvlCode": "S", "SerNotes": null}, "monrec": null, "serrec": null, "relations": null, "relationsRev": null, "addrec": null, "othpubs": null, "ownerships": null, "authors": [{"AutName": "Martin-Cabrera", "Firstname": "Patricia", "Initials": "P.", "Affiliation": "Flanders Marine Institute", "Discriminator": null, "CorporateFlag": 0, "BEntID": 323285, "AutID": 425939, "OrderNr": 1, "DegrID": null, "EditorFlag": 0, "CorrespFlag": 0, "IllustratorFlag": 0, "ReviserFlag": 0, "TranslatorFlag": 0, "InsAcronym": "VLIZ", "InsFSN": "Vlaams Instituut voor de Zee", "ORCID": "0000-0003-3293-5612", "PersID": 37007, "InsID": 36}, {"AutName": "Lombard", "Firstname": "Fabien", "Initials": "F.", "Affiliation": null, "Discriminator": null, "CorporateFlag": 0, "BEntID": 323285, "AutID": 198719, "OrderNr": 2, "DegrID": null, "EditorFlag": 0, "CorrespFlag": 0, "IllustratorFlag": 0, "ReviserFlag": 0, "TranslatorFlag": 0, "InsAcronym": null, "InsFSN": null, "ORCID": null, "PersID": null, "InsID": null}, {"AutName": "Irisson", "Firstname": "Jean-Olivier", "Initials": "J.-O.", "Affiliation": null, "Discriminator": null, "CorporateFlag": 0, "BEntID": 323285, "AutID": 385830, "OrderNr": 3, "DegrID": null, "EditorFlag": 0, "CorrespFlag": 0, "IllustratorFlag": 0, "ReviserFlag": 0, "TranslatorFlag": 0, "InsAcronym": null, "InsFSN": null, "ORCID": null, "PersID": null, "InsID": null}, {"AutName": "Stemmann", "Firstname": "Lars", "Initials": "L.", "Affiliation": null, "Discriminator": null, "CorporateFlag": 0, "BEntID": 323285, "AutID": 54836, "OrderNr": 4, "DegrID": null, "EditorFlag": 0, "CorrespFlag": 0, "IllustratorFlag": 0, "ReviserFlag": 0, "TranslatorFlag": 0, "InsAcronym": null, "InsFSN": null, "ORCID": null, "PersID": null, "InsID": null}, {"AutName": "M\u00f6ller", "Firstname": "Klas", "Initials": "K.O.", "Affiliation": null, "Discriminator": null, "CorporateFlag": 0, "BEntID": 323285, "AutID": 425943, "OrderNr": 5, "DegrID": null, "EditorFlag": 0, "CorrespFlag": 0, "IllustratorFlag": 0, "ReviserFlag": 0, "TranslatorFlag": 0, "InsAcronym": null, "InsFSN": null, "ORCID": null, "PersID": null, "InsID": null}, {"AutName": "Lindh", "Firstname": "Markus", "Initials": "M.", "Affiliation": null, "Discriminator": null, "CorporateFlag": 0, "BEntID": 323285, "AutID": 350115, "OrderNr": 6, "DegrID": null, "EditorFlag": 0, "CorrespFlag": 0, "IllustratorFlag": 0, "ReviserFlag": 0, "TranslatorFlag": 0, "InsAcronym": null, "InsFSN": null, "ORCID": null, "PersID": null, "InsID": null}, {"AutName": "Creach", "Firstname": "Veronique", "Initials": "V.", "Affiliation": null, "Discriminator": null, "CorporateFlag": 0, "BEntID": 323285, "AutID": 253309, "OrderNr": 7, "DegrID": null, "EditorFlag": 0, "CorrespFlag": 0, "IllustratorFlag": 0, "ReviserFlag": 0, "TranslatorFlag": 0, "InsAcronym": null, "InsFSN": null, "ORCID": null, "PersID": null, "InsID": null}, {"AutName": "Schepers", "Firstname": "Lennert", "Initials": "L.", "Affiliation": "Flanders Marine Institute", "Discriminator": null, "CorporateFlag": 0, "BEntID": 323285, "AutID": 425946, "OrderNr": 8, "DegrID": null, "EditorFlag": 0, "CorrespFlag": 0, "IllustratorFlag": 0, "ReviserFlag": 0, "TranslatorFlag": 0, "InsAcronym": "VLIZ", "InsFSN": "Vlaams Instituut voor de Zee", "ORCID": "0000-0002-6145-8248", "PersID": 32873, "InsID": 36}], "mapdetails": null, "datasets": null, "monographs": null, "monparts": null, "serparts": null, "BEntOpen": 323285, "BEntPrivate": null, "availability": [{"BInstID": 351539, "LibID": 36, "BRefID": 329678, "EmbargoDate": null, "FullEmbargoDate": null, "PhysMedID": 16, "hasOCRd": null, "ShelfLocCode": "351539", "BarCode": null, "PaidValue": null, "Medium": "Server", "Description": "VLIZ Open Access", "Acronym": "VLIZ", "Library": "Vlaams Instituut voor de Zee", "DutchTerm": "Open access", "URL": null, "ClassifID": 53, "Classification": "Open access", "ReqLink": null, "ClassifTypID": 1, "URLLocation": "https://www.vliz.be/imisdocs/publications/", "SubDir": null, "InternalReq": 0, "LoggedInReq": 0, "Disclaimer": null, "DutchDisclaimer": null, "FileFormat": ".pdf", "FileDescr": "pdf", "InsPub": 1, "InsID": 36, "FileFormID": 6, "PublicFlag": 1, "orderLib": "A"}], "litstyles": [{"LitStyID": 16, "Style": "Samenvatting"}], "thespers": null, "conf": null, "proj": null, "Physdatasets": null, "spcols": {"222": {"SpName": "BMB - Belgische Mariene Bibliografie", "SpColID": 222, "ParSpColID": null, "TopParID": null, "ShortName": "BMB", "URLLocation": null, "LibID": 36, "OpenRepoFlag": null, "SpTypID": null, "TopParIDNotWebsite": null, "SpColPath": "BMB"}, "918": {"SpName": "EMODnet acknowledged", "SpColID": 918, "ParSpColID": 39, "TopParID": 39, "ShortName": "EMODnet ack", "URLLocation": null, "LibID": 36, "OpenRepoFlag": null, "SpTypID": null, "TopParIDNotWebsite": 39, "SpColPath": "VLIZ ackn/EMODnet ack"}, "980": {"SpName": "EMODnet Biology acknowledged", "SpColID": 980, "ParSpColID": 918, "TopParID": 39, "ShortName": "EMODnet Biology ackn", "URLLocation": null, "LibID": 36, "OpenRepoFlag": null, "SpTypID": null, "TopParIDNotWebsite": 39, "SpColPath": "VLIZ ackn/EMODnet ack/EMODnet Biology ackn"}, "919": {"SpName": "European Oceanographic Biogeographic Information System (EurOBIS) acknowledged", "SpColID": 919, "ParSpColID": 941, "TopParID": 39, "ShortName": "EurOBIS ackn", "URLLocation": null, "LibID": 36, "OpenRepoFlag": null, "SpTypID": null, "TopParIDNotWebsite": 39, "SpColPath": "VLIZ ackn/LifeWatch Species Information Backbone/EurOBIS ackn"}, "992": {"SpName": "FRIS - Flanders Research Information Space", "SpColID": 992, "ParSpColID": null, "TopParID": null, "ShortName": "FRIS", "URLLocation": null, "LibID": 36, "OpenRepoFlag": null, "SpTypID": null, "TopParIDNotWebsite": null, "SpColPath": "FRIS"}, "941": {"SpName": "LifeWatch Species Information Backbone", "SpColID": 941, "ParSpColID": 39, "TopParID": 39, "ShortName": "LifeWatch Species Information Backbone", "URLLocation": null, "LibID": 36, "OpenRepoFlag": null, "SpTypID": null, "TopParIDNotWebsite": 39, "SpColPath": "VLIZ ackn/LifeWatch Species Information Backbone"}, "793": {"SpName": "Marine Regions acknowledged", "SpColID": 793, "ParSpColID": 941, "TopParID": 39, "ShortName": "Marine Regions ackn", "URLLocation": null, "LibID": 36, "OpenRepoFlag": null, "SpTypID": null, "TopParIDNotWebsite": 39, "SpColPath": "VLIZ ackn/LifeWatch Species Information Backbone/Marine Regions ackn"}, "880": {"SpName": "OBIS-cited publications", "SpColID": 880, "ParSpColID": null, "TopParID": null, "ShortName": "OBIS-cited publications", "URLLocation": null, "LibID": 36, "OpenRepoFlag": null, "SpTypID": null, "TopParIDNotWebsite": null, "SpColPath": "OBIS-cited publications"}, "221": {"SpName": "OMA - Open Marien Archief", "SpColID": 221, "ParSpColID": null, "TopParID": null, "ShortName": "OMA", "URLLocation": "http://www.vliz.be/nl/open-marien-archief?module=ref&refid=", "LibID": 36, "OpenRepoFlag": 1, "SpTypID": null, "TopParIDNotWebsite": null, "SpColPath": "OMA"}, "39": {"SpName": "VLIZ Acknowledged Publications", "SpColID": 39, "ParSpColID": null, "TopParID": null, "ShortName": "VLIZ ackn", "URLLocation": null, "LibID": 36, "OpenRepoFlag": null, "SpTypID": null, "TopParIDNotWebsite": null, "SpColPath": "VLIZ ackn"}, "": {"SpName": "VLIZ Core Flag", "SpColID": null, "ParSpColID": null, "TopParID": null, "ShortName": null, "URLLocation": null, "LibID": null, "OpenRepoFlag": null, "SpTypID": 1, "TopParIDNotWebsite": null, "SpColPath": null}, "507": {"SpName": "World Register of Marine Species", "SpColID": 507, "ParSpColID": null, "TopParID": null, "ShortName": "WoRMS website", "URLLocation": null, "LibID": null, "OpenRepoFlag": null, "SpTypID": null, "TopParIDNotWebsite": null, "SpColPath": "WoRMS website"}, "915": {"SpName": "World Register of Marine Species (WoRMS) acknowledged", "SpColID": 915, "ParSpColID": 941, "TopParID": 39, "ShortName": "WoRMS ackn", "URLLocation": null, "LibID": 36, "OpenRepoFlag": null, "SpTypID": null, "TopParIDNotWebsite": 39, "SpColPath": "VLIZ ackn/LifeWatch Species Information Backbone/WoRMS ackn"}, "947": {"SpName": "WoRMS ackn - direct reference", "SpColID": 947, "ParSpColID": 915, "TopParID": 39, "ShortName": "WoRMS ackn - direct", "URLLocation": null, "LibID": 36, "OpenRepoFlag": null, "SpTypID": null, "TopParIDNotWebsite": 39, "SpColPath": "VLIZ ackn/LifeWatch Species Information Backbone/WoRMS ackn/WoRMS ackn - direct"}}, "doi": null, "MParts": null, "SParts": null, "hLibs": null, "langs": [{"BEntID": 323285, "LangCode": "en", "AbstractFlag": 0}, {"BEntID": 323285, "LangCode": "en", "AbstractFlag": 1}], "urls": [{"URL": "https://hdl.handle.net/10.3897/biss.4.58932", "externalID": "10.3897/biss.4.58932", "URLTypeCode": "Handle", "URLID": 86115, "URLTypID": 32, "URLType": "Handle", "URLPrefix": "https://hdl.handle.net/"}], "thesterms": null, "taxterms": null, "geoterms": null, "othterms": null, "asfacodes": null, "asfa2codes": null, "resmessage": "", "complete": 1, "sessions": {"newSesName": "Bouchti, Zohra, Z.", "newSesDate": {"date": "2020-09-30 10:10:57.447000", "timezone_type": 3, "timezone": "Europe/Brussels"}, "updSesName": "Chisala, Chilekwa, C.", "updSesDate": {"date": "2020-11-10 15:17:32.670000", "timezone_type": 3, "timezone": "Europe/Brussels"}}, "arch2discl": 221, "SERpubls": [{"PublName": "Pensoft Publishers", "City": "Sofia"}], "pictures": [], "collections": [{"Collection": "OMA - Open Marien Archief", "ShortName": "OMA"}, {"Collection": "VLIZ Acknowledged Publications", "ShortName": "VLIZ ackn"}]}